MANIFEST.in
README.md
setup.py
mxpi/__init__.py
mxpi/__main__.py
mxpi/cmdpid.log
mxpi/db.sqlite3
mxpi/manage.py
mxpi/mxpi.log
mxpi/version.py
mxpi.egg-info/PKG-INFO
mxpi.egg-info/SOURCES.txt
mxpi.egg-info/dependency_links.txt
mxpi.egg-info/entry_points.txt
mxpi.egg-info/requires.txt
mxpi.egg-info/top_level.txt
mxpi/MxPisite/__init__.py
mxpi/MxPisite/asgi.py
mxpi/MxPisite/routing.py
mxpi/MxPisite/settings.py
mxpi/MxPisite/urls.py
mxpi/MxPisite/wsgi.py
mxpi/MxPisite/__pycache__/__init__.cpython-310.pyc
mxpi/MxPisite/__pycache__/__init__.cpython-37.pyc
mxpi/MxPisite/__pycache__/__init__.cpython-38.pyc
mxpi/MxPisite/__pycache__/__init__.cpython-39.pyc
mxpi/MxPisite/__pycache__/asgi.cpython-310.pyc
mxpi/MxPisite/__pycache__/asgi.cpython-37.pyc
mxpi/MxPisite/__pycache__/asgi.cpython-38.pyc
mxpi/MxPisite/__pycache__/asgi.cpython-39.pyc
mxpi/MxPisite/__pycache__/routing.cpython-310.pyc
mxpi/MxPisite/__pycache__/routing.cpython-37.pyc
mxpi/MxPisite/__pycache__/routing.cpython-38.pyc
mxpi/MxPisite/__pycache__/routing.cpython-39.pyc
mxpi/MxPisite/__pycache__/settings.cpython-310.pyc
mxpi/MxPisite/__pycache__/settings.cpython-37.pyc
mxpi/MxPisite/__pycache__/settings.cpython-38.pyc
mxpi/MxPisite/__pycache__/settings.cpython-39.pyc
mxpi/MxPisite/__pycache__/urls.cpython-310.pyc
mxpi/MxPisite/__pycache__/urls.cpython-37.pyc
mxpi/MxPisite/__pycache__/urls.cpython-38.pyc
mxpi/MxPisite/__pycache__/urls.cpython-39.pyc
mxpi/MxPisite/__pycache__/wsgi.cpython-310.pyc
mxpi/MxPisite/__pycache__/wsgi.cpython-37.pyc
mxpi/MxPisite/__pycache__/wsgi.cpython-38.pyc
mxpi/__pycache__/__init__.cpython-310.pyc
mxpi/__pycache__/__init__.cpython-38.pyc
mxpi/app/__init__.py
mxpi/app/admin.py
mxpi/app/apps.py
mxpi/app/asgi.py
mxpi/app/consumers.py
mxpi/app/models.py
mxpi/app/nbstreamreader.py
mxpi/app/routing.py
mxpi/app/tests.py
mxpi/app/urls.py
mxpi/app/views.py
mxpi/app/websocket.py
mxpi/app/__pycache__/__init__.cpython-310.pyc
mxpi/app/__pycache__/__init__.cpython-37.pyc
mxpi/app/__pycache__/__init__.cpython-38.pyc
mxpi/app/__pycache__/__init__.cpython-39.pyc
mxpi/app/__pycache__/admin.cpython-310.pyc
mxpi/app/__pycache__/admin.cpython-37.pyc
