Metadata-Version: 2.1
Name: mxpi
Version: 1.5.3
Summary: MxPi
Home-page: https://gitee.com/yuanyunqaing/MxPi
Author: YuanYunQiang
Author-email: 649756903@qq.com
License: MIT Licence
Keywords: pip,SICA,featureextraction
Platform: any
